LICENSE
MANIFEST.in
README.md
opendoor.conf
opendoor.py
setup.py
data/directories.back.dat
data/directories.dat
data/ignored.dat
data/proxies.dat
data/subdomains.dat
data/useragents.dat
opendoor.egg-info/PKG-INFO
opendoor.egg-info/SOURCES.txt
opendoor.egg-info/dependency_links.txt
opendoor.egg-info/entry_points.txt
opendoor.egg-info/not-zip-safe
opendoor.egg-info/requires.txt
opendoor.egg-info/top_level.txt
src/__init__.py
src/controller.py
src/exceptions.py
src/core/__init__.py
src/core/core.py
src/core/color/__init__.py
src/core/color/color.py
src/core/decorators/__init__.py
src/core/decorators/timer.py
src/core/filesystem/__init__.py
src/core/filesystem/exceptions.py
src/core/filesystem/filesystem.py
src/core/helper/__init__.py
src/core/helper/helper.py
src/core/http/__init__.py
src/core/http/exceptions.py
src/core/http/http.py
src/core/http/https.py
src/core/http/proxy.py
src/core/http/response.py
src/core/http/socks.py
src/core/http/plugins/__init__.py
src/core/http/plugins/exceptions.py
src/core/http/plugins/response_plugin.py
src/core/http/plugins/response/__init__.py
src/core/http/plugins/response/collation.py
src/core/http/plugins/response/file.py
src/core/http/plugins/response/indexof.py
src/core/http/plugins/response/skipempty.py
src/core/http/plugins/response/skipsizes.py
src/core/http/plugins/response/provider/__init__.py
src/core/http/plugins/response/provider/provider.py
src/core/http/providers/__init__.py
src/core/http/providers/accept.py
src/core/http/providers/cache.py
src/core/http/providers/connection.py
src/core/http/providers/cookies.py
src/core/http/providers/debug.py
src/core/http/providers/header.py
src/core/http/providers/request.py
src/core/http/providers/response.py
src/core/http/providers/user_agent.py
src/core/logger/__init__.py
src/core/logger/colorize.py
src/core/logger/config.py
src/core/logger/exception.py
src/core/logger/logger.py
src/core/logger/rainbow.py
src/core/options/__init__.py
src/core/options/exceptions.py
src/core/options/filter.py
src/core/options/options.py
src/core/system/__init__.py
src/core/system/exceptions.py
src/core/system/output.py
src/core/system/process.py
src/core/system/terminal.py
src/lib/__init__.py
