Metadata-Version: 2.1
Name: opendoor
Version: 4.2.0
Summary: OWASP WEB Directory Scanner
Home-page: https://github.com/stanislav-web/OpenDoor
Author: Brain Storm Team
Author-email: nomail@gmail.com
Maintainer: Brain Storm Team
Maintainer-email: nomail@gmail.com
License: GPL
Download-URL: https://github.com/stanislav-web/OpenDoor/archive/refs/heads/master.zip
Keywords: owasp scanner,directory scanner,access directory scanner,fuzzer,auth scanner,dir search,dirmap
Platform: any
Classifier: Development Status :: 5 - Production/Stable
Classifier: Natural Language :: English
Classifier: Intended Audience :: Developers
Classifier: Operating System :: MacOS
Classifier: Operating System :: Unix
Classifier: License :: OSI Approved :: GNU General Public License v3 (GPLv3)
Classifier: Programming Language :: Python
Classifier: Programming Language :: Python :: 3
Classifier: Topic :: Utilities
Classifier: Topic :: Internet :: WWW/HTTP :: Site Management :: Link Checking
Classifier: Topic :: Internet :: WWW/HTTP :: Indexing/Search
Classifier: Topic :: Internet :: WWW/HTTP :: WSGI :: Application
License-File: LICENSE
